{"cameraMode":{"drawMode":0,"name":"Shaded","section":"Shading Mode"},"sceneLighting":true,"audioPlay":false,"sceneViewState":{"showFog":true,"showMaterialUpdate":false,"showSkybox":true,"showFlares":true,"showImageEffects":true,"showParticleSystems":true},"in2DMode":false,"pivot":{"x":-198.28070068359376,"y":227.95254516601563,"z":-21.098724365234376},"rotation":{"x":0.02942102588713169,"y":0.9574878811836243,"z":-0.10556604713201523,"w":0.26684996485710146},"size":469.61761474609377,"orthographic":false}